<?xml version="1.0"?><content>
<EMPLOYEE>
	<id>51913318036811</id>
	<name>Emplyee5</name>
	<salary>2450</salary>
	<isDead>false</isDead>
	<workingHours>2.1639245715679447</workingHours>
	<DISCRIMINANT>Caretaker</DISCRIMINANT>
</EMPLOYEE>
<EMPLOYEE>
	<id>98796244007735</id>
	<name>Emplyee4</name>
	<salary>4000</salary>
	<isDead>false</isDead>
	<workingHours>6.805825233980506</workingHours>
	<DISCRIMINANT>Caretaker</DISCRIMINANT>
</EMPLOYEE>
<EMPLOYEE>
	<id>71715047900917</id>
	<name>Emplyee3</name>
	<salary>4000</salary>
	<isDead>false</isDead>
	<workingHours>5.309736899444242</workingHours>
	<DISCRIMINANT>Caretaker</DISCRIMINANT>
</EMPLOYEE>
<EMPLOYEE>
	<id>59843128437108</id>
	<name>Emplyee5</name>
	<salary>2450</salary>
	<isDead>false</isDead>
	<workingHours>6.729189712351606</workingHours>
	<DISCRIMINANT>Caretaker</DISCRIMINANT>
</EMPLOYEE>
<EMPLOYEE>
	<id>2821457451896</id>
	<name>Emplyee4</name>
	<salary>1500</salary>
	<isDead>false</isDead>
	<workingHours>4.558558050567554</workingHours>
	<DISCRIMINANT>Caretaker</DISCRIMINANT>
</EMPLOYEE>
<EMPLOYEE>
	<id>87314491871754</id>
	<name>Emplyee5</name>
	<salary>2450</salary>
	<isDead>false</isDead>
	<workingHours>6.91689298793826</workingHours>
	<DISCRIMINANT>Caretaker</DISCRIMINANT>
</EMPLOYEE>
<EMPLOYEE>
	<id>56365004497962</id>
	<name>Emplyee5</name>
	<salary>2450</salary>
	<isDead>false</isDead>
	<workingHours>0.3387943383420149</workingHours>
	<DISCRIMINANT>Caretaker</DISCRIMINANT>
</EMPLOYEE>
<EMPLOYEE>
	<id>24307594917367</id>
	<name>Emplyee3</name>
	<salary>8000</salary>
	<isDead>false</isDead>
	<workingHours>5.831739537108027</workingHours>
	<DISCRIMINANT>Caretaker</DISCRIMINANT>
</EMPLOYEE>
<EMPLOYEE>
	<id>50451979101923</id>
	<name>Emplyee2</name>
	<salary>4000</salary>
	<isDead>false</isDead>
	<workingHours>1.2013066224232487</workingHours>
	<DISCRIMINANT>Caretaker</DISCRIMINANT>
</EMPLOYEE>
</content>